blacklight/.DS_Store
blacklight/__init__.py
blacklight/autoML/__init__.py
blacklight/autoML/_convolutional_nn.py
blacklight/engine/.DS_Store
blacklight/engine/__init__.py
blacklight/engine/adapters/__init__.py
blacklight/engine/adapters/adapter.py
blacklight/engine/adapters/tests/__init__.py
blacklight/engine/adapters/tests/test_adapter.py
blacklight/engine/analyzers/__init__.py
blacklight/engine/data/__init__.py
blacklight/engine/data/blacklight_dataset.py
blacklight/engine/data/tests/__init__.py
blacklight/engine/data/tests/data/Iris.csv
blacklight/engine/data/tests/data/Iris.json
blacklight/engine/data/tests/data/Iris.parquet
blacklight/engine/data/tests/data/Iris.xlsx
blacklight/engine/data/tests/data/__init__.py
blacklight/engine/data/tests/data/csv_to_other_datatypes.py
blacklight/engine/data/tests/test_blacklight_dataset.py
blacklight/engine/model_creator.py
blacklight/engine/model_options.py
blacklight/engine/tests/__init__.py
blacklight/engine/tests/test_model_creator.py
blacklight/engine/tests/test_model_options.py
blacklight/engine/utils/.DS_Store
blacklight/engine/utils/__init__.py
blacklight/engine/utils/data_utils.py
blacklight/engine/utils/tests/__init__.py
blacklight/engine/utils/tests/test_data_utils.py
blacklight/genetic/.DS_Store
blacklight/genetic/__init__.py
blacklight/genetic/base/__init__.py
blacklight/genetic/base/chromosome.py
blacklight/genetic/base/individual.py
blacklight/genetic/base/population.py
blacklight/genetic/chromosomes/.DS_Store
blacklight/genetic/chromosomes/__init__.py
blacklight/genetic/chromosomes/convolutional_chromosome.py
blacklight/genetic/chromosomes/feed_forward_chromosome.py
blacklight/genetic/chromosomes/tests/__init__.py
blacklight/genetic/chromosomes/tests/test_feed_forward_chromosome.py
blacklight/genetic/individuals/__init__.py
blacklight/genetic/individuals/convolution_individual.py
blacklight/genetic/individuals/feed_forward_individual.py
blacklight/genetic/individuals/tests/__init__.py
blacklight-0.1.11.dist-info/LICENSE
blacklight-0.1.11.dist-info/METADATA
blacklight-0.1.11.dist-info/WHEEL
blacklight-0.1.11.dist-info/RECORD
