Metadata-Version: 2.1
Name: blacklight
Version: 0.1.11
Summary: AutoML utilizing Genetic Algorithms and Neural Networks
Author: Cole Agard
Author-email: ctagard19@gmail.com
Requires-Python: >=3.9,<3.11
Classifier: Programming Language :: Python :: 3
Classifier: Programming Language :: Python :: 3.9
Classifier: Programming Language :: Python :: 3.10
Requires-Dist: fastparquet
Requires-Dist: matplotlib
Requires-Dist: numpy
Requires-Dist: openpyxl
Requires-Dist: pandas
Requires-Dist: scikit-learn
Requires-Dist: tensorflow ; platform_machine != "arm64" and sys_platform != "darwin"
Requires-Dist: tensorflow-macos ; platform_machine == "arm64" and sys_platform == "darwin"
Requires-Dist: tensorflow-metal ; platform_machine == "arm64" and sys_platform == "darwin"
Requires-Dist: tqdm
